zivlons/__init__.py
zivlons/netonics.py
netonics-0.0.1.dist-info/METADATA
netonics-0.0.1.dist-info/WHEEL
netonics-0.0.1.dist-info/top_level.txt
netonics-0.0.1.dist-info/RECORD
